{
  "orders": {
    "234582": {
      "delivery_date": "6/10/2026"
    },
    "234583": {
      "delivery_date": "6/10/2026"
    },
    "234584": {
      "delivery_date": "6/10/2026"
    },
    "234585": {
      "delivery_date": "6/10/2026"
    },
    "234586": {
      "delivery_date": "6/10/2026"
    },
    "234587": {
      "delivery_date": "6/10/2026"
    },
    "234588": {
      "delivery_date": "6/10/2026"
    },
    "234589": {
      "delivery_date": "6/10/2026"
    },
    "234590": {
      "delivery_date": "6/10/2026"
    },
    "234591": {
      "delivery_date": "6/10/2026"
    },
    "234592": {
      "delivery_date": "6/10/2026"
    },
    "234593": {
      "delivery_date": "6/10/2026"
    },
    "234594": {
      "delivery_date": "6/10/2026"
    },
    "234595": {
      "delivery_date": "6/10/2026"
    },
    "234596": {
      "delivery_date": "6/10/2026"
    },
    "234597": {
      "delivery_date": "6/10/2026"
    },
    "234598": {
      "delivery_date": "6/10/2026"
    },
    "234599": {
      "delivery_date": "6/10/2026"
    },
    "234601": {
      "delivery_date": "6/10/2026"
    },
    "234602": {
      "delivery_date": "6/10/2026"
    },
    "234667": {
      "delivery_date": "6/11/2026"
    },
    "234668": {
      "delivery_date": "6/11/2026"
    },
    "234669": {
      "delivery_date": "6/11/2026"
    },
    "234670": {
      "delivery_date": "6/11/2026"
    },
    "234671": {
      "delivery_date": "6/11/2026"
    },
    "234672": {
      "delivery_date": "6/11/2026"
    },
    "234673": {
      "delivery_date": "6/11/2026"
    },
    "234674": {
      "delivery_date": "6/11/2026"
    },
    "234717": {
      "delivery_date": "6/12/2026"
    },
    "234718": {
      "delivery_date": "6/12/2026"
    },
    "234719": {
      "delivery_date": "6/12/2026"
    },
    "234720": {
      "delivery_date": "6/12/2026"
    },
    "234721": {
      "delivery_date": "6/12/2026"
    },
    "234722": {
      "delivery_date": "6/12/2026"
    },
    "234723": {
      "delivery_date": "6/12/2026"
    },
    "234724": {
      "delivery_date": "6/12/2026"
    },
    "234725": {
      "delivery_date": "6/12/2026"
    },
    "234726": {
      "delivery_date": "6/12/2026"
    },
    "234727": {
      "delivery_date": "6/12/2026"
    },
    "234728": {
      "delivery_date": "6/12/2026"
    },
    "234729": {
      "delivery_date": "6/12/2026"
    },
    "234730": {
      "delivery_date": "6/12/2026"
    },
    "234731": {
      "delivery_date": "6/12/2026"
    },
    "234732": {
      "delivery_date": "6/12/2026"
    },
    "234733": {
      "delivery_date": "6/12/2026"
    },
    "234769": {
      "delivery_date": "6/15/2026"
    },
    "234770": {
      "delivery_date": "6/15/2026"
    },
    "234771": {
      "delivery_date": "6/15/2026"
    },
    "234772": {
      "delivery_date": "6/12/2026"
    },
    "234773": {
      "delivery_date": "6/12/2026"
    },
    "234777": {
      "delivery_date": "6/15/2026"
    },
    "234778": {
      "delivery_date": "6/15/2026"
    },
    "234779": {
      "delivery_date": "6/15/2026"
    },
    "234780": {
      "delivery_date": "6/15/2026"
    },
    "234781": {
      "delivery_date": "6/15/2026"
    },
    "234782": {
      "delivery_date": "6/15/2026"
    },
    "234783": {
      "delivery_date": "6/15/2026"
    },
    "234833": {
      "delivery_date": "6/12/2026"
    },
    "234834": {
      "delivery_date": "6/12/2026"
    },
    "234879": {
      "delivery_date": "6/12/2026"
    },
    "234880": {
      "delivery_date": "6/12/2026"
    },
    "234881": {
      "delivery_date": "6/12/2026"
    },
    "234882": {
      "delivery_date": "6/12/2026"
    },
    "234883": {
      "delivery_date": "6/12/2026"
    },
    "234884": {
      "delivery_date": "6/12/2026"
    },
    "234885": {
      "delivery_date": "6/12/2026"
    },
    "234886": {
      "delivery_date": "6/12/2026"
    },
    "234887": {
      "delivery_date": "6/12/2026"
    },
    "234888": {
      "delivery_date": "6/18/2026"
    },
    "234889": {
      "delivery_date": "6/12/2026"
    },
    "234897": {
      "delivery_date": "6/17/2026"
    },
    "234898": {
      "delivery_date": "6/17/2026"
    },
    "234899": {
      "delivery_date": "6/17/2026"
    },
    "234900": {
      "delivery_date": "6/17/2026"
    },
    "234901": {
      "delivery_date": "6/17/2026"
    },
    "234902": {
      "delivery_date": "6/17/2026"
    },
    "234903": {
      "delivery_date": "6/17/2026"
    },
    "234904": {
      "delivery_date": "6/17/2026"
    },
    "234941": {
      "delivery_date": "6/18/2026"
    },
    "234942": {
      "delivery_date": "6/18/2026"
    },
    "234943": {
      "delivery_date": "6/18/2026"
    },
    "234944": {
      "delivery_date": "6/18/2026"
    },
    "234945": {
      "delivery_date": "6/18/2026"
    },
    "234946": {
      "delivery_date": "6/17/2026"
    },
    "234991": {
      "delivery_date": "6/19/2026"
    },
    "234992": {
      "delivery_date": "6/19/2026"
    },
    "234993": {
      "delivery_date": "6/19/2026"
    },
    "234994": {
      "delivery_date": "6/19/2026"
    },
    "234995": {
      "delivery_date": "6/18/2026"
    },
    "234996": {
      "delivery_date": "6/19/2026"
    },
    "234997": {
      "delivery_date": "6/19/2026"
    },
    "234998": {
      "delivery_date": "6/19/2026"
    },
    "234999": {
      "delivery_date": "6/19/2026"
    },
    "235000": {
      "delivery_date": "6/19/2026"
    },
    "235001": {
      "delivery_date": "6/19/2026"
    },
    "235002": {
      "delivery_date": "6/18/2026"
    },
    "235083": {
      "delivery_date": "6/23/2026"
    },
    "235084": {
      "delivery_date": "6/23/2026"
    },
    "235085": {
      "delivery_date": "6/23/2026"
    },
    "235086": {
      "delivery_date": "6/23/2026"
    },
    "235087": {
      "delivery_date": "6/23/2026"
    },
    "235131": {
      "delivery_date": "6/24/2026"
    },
    "235132": {
      "delivery_date": "6/24/2026"
    },
    "235133": {
      "delivery_date": "6/24/2026"
    },
    "235134": {
      "delivery_date": "6/25/2026"
    },
    "235135": {
      "delivery_date": "6/23/2026"
    },
    "235136": {
      "delivery_date": "6/23/2026"
    },
    "235138": {
      "delivery_date": "6/24/2026"
    },
    "235140": {
      "delivery_date": "6/24/2026"
    },
    "235141": {
      "delivery_date": "6/24/2026"
    },
    "235142": {
      "delivery_date": "6/24/2026"
    },
    "235143": {
      "delivery_date": "6/24/2026"
    },
    "235144": {
      "delivery_date": "6/24/2026"
    },
    "235145": {
      "delivery_date": "6/24/2026"
    },
    "235146": {
      "delivery_date": "6/24/2026"
    },
    "235147": {
      "delivery_date": "6/24/2026"
    },
    "235148": {
      "delivery_date": "6/24/2026"
    },
    "235149": {
      "delivery_date": "6/24/2026"
    },
    "235160": {
      "delivery_date": "6/22/2026"
    },
    "235161": {
      "delivery_date": "6/24/2026"
    },
    "235191": {
      "delivery_date": "6/22/2026",
      "last_processed": "2026-06-18 15:29:05",
      "output_pdf": "C:\\Users\\brandon.m.smith\\My Projects\\Showers Programmer\\Output\\Runs\\Batch5941_5\\Sketches\\235191.pdf",
      "remake_items": [],
      "report_path": "C:\\Users\\brandon.m.smith\\My Projects\\Showers Programmer\\Output\\Runs\\Batch5941_5\\Reports\\235191_programming_report.txt",
      "run_folder": "C:\\Users\\brandon.m.smith\\My Projects\\Showers Programmer\\Output\\Runs\\Batch5941_5",
      "status": "ISSUES"
    },
    "235192": {
      "delivery_date": "6/22/2026",
      "last_processed": "2026-06-18 15:29:05",
      "output_pdf": "C:\\Users\\brandon.m.smith\\My Projects\\Showers Programmer\\Output\\Runs\\Batch5941_5\\Sketches\\235192.pdf",
      "remake_items": [],
      "report_path": "C:\\Users\\brandon.m.smith\\My Projects\\Showers Programmer\\Output\\Runs\\Batch5941_5\\Reports\\235192_programming_report.txt",
      "run_folder": "C:\\Users\\brandon.m.smith\\My Projects\\Showers Programmer\\Output\\Runs\\Batch5941_5",
      "status": "ISSUES"
    },
    "235193": {
      "delivery_date": "6/22/2026",
      "last_processed": "2026-06-18 15:29:05",
      "output_pdf": "C:\\Users\\brandon.m.smith\\My Projects\\Showers Programmer\\Output\\Runs\\Batch5941_5\\Sketches\\235193.pdf",
      "remake_items": [],
      "report_path": "C:\\Users\\brandon.m.smith\\My Projects\\Showers Programmer\\Output\\Runs\\Batch5941_5\\Reports\\235193_programming_report.txt",
      "run_folder": "C:\\Users\\brandon.m.smith\\My Projects\\Showers Programmer\\Output\\Runs\\Batch5941_5",
      "status": "ISSUES"
    },
    "235194": {
      "delivery_date": "6/24/2026",
      "last_processed": "2026-06-18 15:29:00",
      "output_pdf": "C:\\Users\\brandon.m.smith\\My Projects\\Showers Programmer\\Output\\Runs\\Batch5941_4\\Sketches\\235194.pdf",
      "report_path": "C:\\Users\\brandon.m.smith\\My Projects\\Showers Programmer\\Output\\Runs\\Batch5941_4\\Reports\\235194_programming_report.txt",
      "run_folder": "C:\\Users\\brandon.m.smith\\My Projects\\Showers Programmer\\Output\\Runs\\Batch5941_4",
      "status": "OK"
    },
    "235195": {
      "delivery_date": "6/24/2026",
      "last_processed": "2026-06-18 15:29:00",
      "output_pdf": "C:\\Users\\brandon.m.smith\\My Projects\\Showers Programmer\\Output\\Runs\\Batch5941_4\\Sketches\\235195.pdf",
      "report_path": "C:\\Users\\brandon.m.smith\\My Projects\\Showers Programmer\\Output\\Runs\\Batch5941_4\\Reports\\235195_programming_report.txt",
      "run_folder": "C:\\Users\\brandon.m.smith\\My Projects\\Showers Programmer\\Output\\Runs\\Batch5941_4",
      "status": "OK"
    }
  }
}